[	{
		"0":[0],
		"filepath":"background.gif",
		"name":"BACKGROUND"
	},
	{		
		"1":[1,2,3,4,5,6,7,8,9,10,11,12,13,14,15],
		"2":[1,2,3,4,5,6,7,8,9,10,11,12,13,14,15],
		"3":[1,2,3,4,5,6,7,8,9,10,11,12,13,14,15],
		"4":[1,2,3,4,5,6,7,8,9,10,11,12,13,14,15],
		"5":[1,2,3,4,5,6,7,8,9,10,11,12,13,14,15],
		"6":[1,2,3,4,5,6,7,8,9,10,11,12,13,14,15],
		"7":[1,2,3,4,5,6,7,8,9,10,11,12,13,14,15],
		"8":[1,2,3,4,5,6,7,8,9,10,11,12,13,14,15],
		"9":[1,2,3,4,5,6,7,8,9,10,11,12,13,14,15],
		"10":[1,2,3,4,5,6,7,8,9,10,11,12,13,14,15],
		"11":[1,2,3,4,5,6,7,8,9,10,11,12,13,14,15],
		"12":[1,2,3,4,5,6,7,8,9,10,11,12,13,14,15],
		"13":[1,2,3,4,5,6,7,8,9,10,11,12,13,14,15],
		"14":[1,2,3,4,5,6,7,8,9,10,11,12,13,14,15],
		"15":[1,2,3,4,5,6,7,8,9,10,11,12,13,14,15],
		"filepath":"ground.gif",
		"name":"GROUND"
	},
	{			
		"1":[6],
		"3":[2,9,11,13],
		"4":[2,9,11,13],
		"5":[2,4,9,11,13],
		"6":[11],
		"7":[11,14],
		"8":[11,14],
		"9":[2,14],
		"10":[2,11],
		"11":[4,13],
		"12":[13],
		"13":[13],
		"15":[2,12],
		"filepath":"verticalWallSection.gif",
		"name":"WALL"
	},
	{
		"2":[1,2,3,4,6,7,8,9,10,11,13,14],
		"4":[4,5,6,7],
		"5":[14,15],
		"6":[2,3,4,5,6,8,9],
		"7":[13],
		"8":[2,3,4,5,7,8,9,10],
		"9":[13],
		"10":[4,5,6,7,8,9],
		"11":[11,12,15],
		"12":[1,2,3,4,5,6,8,9,10,11,15],
		"14":[2,3,4,5,6,7,8,10,11,12,13,14],
		"filepath":"horizontalWallSection.gif",
		"name":"WALL"
	},
	{
		"0":[1,2,3,4,5,6,7,8,9,10,11,12,13,14,15],
		"filepath":"topWall.gif",
		"name":"WALL"
	},
	{
		"16":[1,2,3,4,5,6,7,8,9,10,11,12,13,14,15],
		"filepath":"bottomWall.gif",
		"name":"WALL"
	},
	{
		"1":[0],
		"2":[0],
		"3":[0],
		"4":[0],
		"5":[0],
		"6":[0],
		"7":[0],
		"8":[0],
		"9":[0],
		"10":[0],
		"11":[0],
		"12":[0],
		"13":[0],
		"14":[0],
		"15":[0],
		"filepath":"leftWall.gif",
		"name":"WALL"
	},
	{
		"1":[16],
		"2":[16],
		"3":[16],
		"4":[16],
		"5":[16],
		"6":[16],
		"7":[16],
		"8":[16],
		"9":[16],
		"10":[16],
		"11":[16],
		"12":[16],
		"13":[16],
		"14":[16],
		"15":[16],
		"filepath":"rightWall.gif",
		"name":"WALL"
	},
	{
		"0":[0],
		"filepath":"topLeftCorner.gif",
		"name":"WALL"
	},
	{
		"0":[16],
		"filepath":"topRightCorner.gif",
		"name":"WALL"
	},
	{
		"16":[16],
		"filepath":"bottomRightCorner.gif",
		"name":"WALL"
	},
	{
		"16":[0],
		"filepath":"bottomLeftCorner.gif",
		"name":"WALL"
	},
	{
		"8":[15],
		"filepath":"murdoc.gif",
		"name":"MURDOC"
	},
	{
		"0":[17],
		"filepath":"needle.gif",
		"name":"NEEDLE_HUD"
	},
	{
		"1":[17],
		"filepath":"syringe.gif",
		"name":"SYRINGE_HUD"
	},
	{
		"2":[17],
		"filepath":"ether_beaker.gif",
		"name":"ETHER_BEAKER_HUD"
	},
	{
		"3":[1],
		"filepath":"mcGyver.gif",
		"name":"MCGYVER"
	}
]